more.cors-0.3-py3.7-nspkg.pth
more/cors/__init__.py
more/cors/action.py
more/cors/main.py
more/cors/tests/test_cors.py
more.cors-0.3.dist-info/LICENSE.txt
more.cors-0.3.dist-info/METADATA
more.cors-0.3.dist-info/WHEEL
more.cors-0.3.dist-info/entry_points.txt
more.cors-0.3.dist-info/namespace_packages.txt
more.cors-0.3.dist-info/top_level.txt
more.cors-0.3.dist-info/RECORD
