Metadata-Version: 2.1
Name: more.cors
Version: 0.3
Summary: CORS support for Morepath
Home-page: http://github.com/kagesenshi/more.cors
Author: Izhar Firdaus
Author-email: kagesenshi.87@gmail.com
License: BSD
Keywords: morepath CORS
Platform: UNKNOWN
Classifier: Intended Audience :: Developers
Classifier: License :: OSI Approved :: BSD License
Classifier: Programming Language :: Python :: 3.4
Classifier: Programming Language :: Python :: 3.5
Classifier: Programming Language :: Python :: 3.6
Classifier: Programming Language :: Python :: 3.7
Classifier: Programming Language :: Python :: 3.8
Classifier: Programming Language :: Python :: Implementation :: PyPy
Requires-Dist: setuptools
Requires-Dist: morepath (>=0.19)
Provides-Extra: coverage
Requires-Dist: pytest-cov ; extra == 'coverage'
Provides-Extra: pep8
Requires-Dist: flake8 ; extra == 'pep8'
Requires-Dist: black ; extra == 'pep8'
Provides-Extra: test
Requires-Dist: pytest ; extra == 'test'
Requires-Dist: pytest-remove-stale-bytecode ; extra == 'test'
Requires-Dist: webtest ; extra == 'test'
